poker_h/__init__.py
poker_h/main.py
poker_h-1.0.2.dist-info/METADATA
poker_h-1.0.2.dist-info/WHEEL
poker_h-1.0.2.dist-info/top_level.txt
poker_h-1.0.2.dist-info/RECORD
