Metadata-Version: 2.1
Name: poker-h
Version: 1.0.2
Summary: This is a library that will help you create a poker game.
Home-page: https://github.com/windgim
Author: Gimer
Author-email: bashinsky04@gmail.com
Project-URL: GitHub, https://github.com/windgim
Keywords: poker pokerh poker-h holdem texas game
Classifier: Programming Language :: Python :: 3.11
Classifier: License :: OSI Approved :: MIT License
Classifier: Operating System :: OS Independent
Requires-Python: >=3.6
Requires-Dist: requests>=2.25.1
